ace_agents/__init__.py
ace_agents/ace_framework.py
ace_agents/agents.py
ace_agents/context.py
ace_agents/llm_client.py
ace_agents/utils.py
ace_agents-0.1.1.dist-info/METADATA
ace_agents-0.1.1.dist-info/WHEEL
ace_agents-0.1.1.dist-info/licenses/LICENSE
ace_agents-0.1.1.dist-info/RECORD
