Metadata-Version: 2.4
Name: ace-agents
Version: 0.1.1
Summary: ACE (Agentic Context Engineering) - A framework for adaptive context optimization using LLM agents
License-File: LICENSE
Requires-Python: >=3.10
Requires-Dist: numpy>=1.24.0
Requires-Dist: pydantic>=2.0.0
Requires-Dist: pyyaml>=6.0
Requires-Dist: requests>=2.31.0
Requires-Dist: sentence-transformers>=2.2.0
Provides-Extra: dev
Requires-Dist: black>=23.0.0; extra == 'dev'
Requires-Dist: mypy>=1.5.0; extra == 'dev'
Requires-Dist: pytest-cov>=4.1.0; extra == 'dev'
Requires-Dist: pytest>=7.4.0; extra == 'dev'
Requires-Dist: python-dotenv>=1.0.0; extra == 'dev'
Requires-Dist: ruff>=0.1.0; extra == 'dev'
Requires-Dist: tqdm>=4.66.0; extra == 'dev'
Requires-Dist: twine>=6.2.0; extra == 'dev'
